[
  {
    "id": "1",
    "name": "Жакупбекова Дарина",
    "login": "zhakupbekova.dar61",
    "password": "2d937fUSHbm!"
  },
  {
    "id": "2",
    "name": "Иргалиев Аян Талгатович",
    "login": "irgaliev.aya18",
    "password": "M!PR55ZQUGUn"
  },
  {
    "id": "3",
    "name": "Амангалиева Камила",
    "login": "amangalieva.kam84",
    "password": "u@TRMs2JhkpK"
  },
  {
    "id": "4",
    "name": "Әсет Фараби Азаматұлы",
    "login": "aset.far82",
    "password": "g95vH@gf3XX3"
  },
  {
    "id": "5",
    "name": "Нургалиев Аслан",
    "login": "nurgaliev.asl80",
    "password": "H9MDX23!nXWj"
  },
  {
    "id": "6",
    "name": "Куантханов Алихан Серикович",
    "login": "kuanthanov.ali51",
    "password": "Ypd2U%xLWZX4"
  },
  {
    "id": "7",
    "name": "Митанова Айнур",
    "login": "mitanova.ayn63",
    "password": "M39XQY45!GFW"
  },
  {
    "id": "8",
    "name": "Акан Алмат Маратович",
    "login": "akan.alm70",
    "password": "4Wf9j@DYJVDa"
  },
  {
    "id": "9",
    "name": "Оразбек Жигер Дидарулы",
    "login": "orazbek.zhi66",
    "password": "7WsFd9$uzYfR"
  },
  {
    "id": "10",
    "name": "Идрисова Дайана Айбековна",
    "login": "idrisova.day19",
    "password": "PWt%ND78xQCK"
  },
  {
    "id": "11",
    "name": "Тулеметов Эльдар Халмуратович",
    "login": "tulemetov.eld74",
    "password": "Hn!fLTtAq2TV"
  },
  {
    "id": "12",
    "name": "Байдурина Меруерт Болатовна",
    "login": "baydurina.mer65",
    "password": "PgzP2EZ0XFj#"
  },
  {
    "id": "13",
    "name": "Байлепесова Нурай Көбболсынқызы",
    "login": "baylepesova.nur49",
    "password": "cbrYV%Jgh29t"
  },
  {
    "id": "14",
    "name": "Кызылтаева Адия Идеяткызы",
    "login": "kyzyltaeva.adi61",
    "password": "rULW9GMdpN!5"
  },
  {
    "id": "15",
    "name": "Кенесова Гульсизим Жараскызы",
    "login": "kenesova.gul21",
    "password": "ACS8k2@8c34H"
  },
  {
    "id": "16",
    "name": "Нуркенова Толкын Сырымовна",
    "login": "nurkenova.tol51",
    "password": "4kzZsfWkC@4k"
  },
  {
    "id": "17",
    "name": "Сабыржан Айсұлтан Бауыржанұлы",
    "login": "sabyrzhan.ays51",
    "password": "DR2NB!rxn9kd"
  },
  {
    "id": "18",
    "name": "Маулешов Дияр Мадиярович",
    "login": "mauleshov.diy28",
    "password": "qrxJMWj6$XqJ"
  },
  {
    "id": "19",
    "name": "Скосарева Лиана Дмитриевна",
    "login": "skosareva.lia99",
    "password": "AMs34cKZj$gj"
  },
  {
    "id": "20",
    "name": "Сәлімқызы Сая",
    "login": "salimqyzy.say11",
    "password": "fd$3kMPZMaMc"
  },
  {
    "id": "21",
    "name": "Ертай Мансур Жанатович",
    "login": "ertay.man19",
    "password": "CtS97!g6y2bx"
  },
  {
    "id": "22",
    "name": "Капаров Биарыс Худайбергенұлы",
    "login": "kaparov.bia47",
    "password": "8SD9W072X!Qm"
  },
  {
    "id": "23",
    "name": "Аншыбай Бексултан Болатұлы",
    "login": "anshybay.bek88",
    "password": "ztqMy6u!JXg6"
  },
  {
    "id": "24",
    "name": "Иралимова Томирис Батырханқызы",
    "login": "iralimova.tom58",
    "password": "p7Fr$58qhseX"
  },
  {
    "id": "25",
    "name": "Жакин Альмухаммед Олжасулы",
    "login": "zhakin.alm22",
    "password": "74j5RkeB@23d"
  },
  {
    "id": "26",
    "name": "Козайдар Мадина Маратқызы",
    "login": "kozaydar.mad96",
    "password": "qh!7PQ9Wd62a"
  },
  {
    "id": "27",
    "name": "Әміржанұлы Сұлтан",
    "login": "amirzhanuly.sul28",
    "password": "ULPqt!BLF6kS"
  },
  {
    "id": "28",
    "name": "Микитчик Дмитрий Александрович",
    "login": "mikitchik.dmi76",
    "password": "q9wBF%gmd3eE"
  },
  {
    "id": "29",
    "name": "Дауыл Думан",
    "login": "dauyl.dum12",
    "password": "r3KpmRKd5a#N"
  },
  {
    "id": "30",
    "name": "Бауыржан Асель Канатқызы",
    "login": "bauyrzhan.ase23",
    "password": "ZsS2$y7pDQ55"
  },
  {
    "id": "31",
    "name": "Скосарев Даниил Дмитриевич",
    "login": "skosarev.dan73",
    "password": "956gQttpy@TV"
  },
  {
    "id": "32",
    "name": "Ахметжан Алтынай",
    "login": "ahmetzhan.alt40",
    "password": "Ne%PeT99BmMb"
  },
  {
    "id": "33",
    "name": "Нугуманова Асем Кайраткызы",
    "login": "nugumanova.ase65",
    "password": "NWnmS7kQgp$g"
  },
  {
    "id": "34",
    "name": "Барлыбаева Дария Саяновна",
    "login": "barlybaeva.dar37",
    "password": "PqLVcT$5Lm50"
  },
  {
    "id": "35",
    "name": "Кенжебай Айша Олжабакызы",
    "login": "kenzhebay.ays45",
    "password": "e8S2zsW5k@4e"
  },
  {
    "id": "36",
    "name": "Сатыбалды Алинур Кайратулы",
    "login": "satybaldy.ali97",
    "password": "cvN!4ucMKJgw"
  },
  {
    "id": "37",
    "name": "Тургумбаев Санжар Нурланович",
    "login": "turgumbaev.san80",
    "password": "vNKEBj9g2!6B"
  },
  {
    "id": "38",
    "name": "Менкин Мансур",
    "login": "menkin.man55",
    "password": "5YXq%TgvYJQM"
  },
  {
    "id": "39",
    "name": "Сманжан Рахат Бакытканулы",
    "login": "smanzhan.rah48",
    "password": "BGX#JV5FgZQ8"
  },
  {
    "id": "40",
    "name": "Назарова Малика Катталбековна",
    "login": "nazarova.mal63",
    "password": "aq46sLwRD7H#"
  },
  {
    "id": "41",
    "name": "Нурпеисов Эмир Рахимжанов",
    "login": "nurpeisov.emi41",
    "password": "9g8f88vh$xq9"
  },
  {
    "id": "42",
    "name": "Ернурулы Нуразим",
    "login": "ernuruly.nur44",
    "password": "7wB$aa2MgFq8"
  },
  {
    "id": "43",
    "name": "Мыңжасарова Оразгул Ахметқызы",
    "login": "mynzhasarova.ora29",
    "password": "M$WqeqENB97b"
  },
  {
    "id": "44",
    "name": "Тугунбаева Малика Бейбутовна",
    "login": "tugunbaeva.mal34",
    "password": "Zbyg#vWvD1Ee"
  },
  {
    "id": "45",
    "name": "Ерхатқызы Айбибі",
    "login": "erhatqyzy.ayb70",
    "password": "!bYjJr4qGXyr"
  },
  {
    "id": "46",
    "name": "Колташев Дмитрий Максимович",
    "login": "koltashev.dmi74",
    "password": "AVG12y3U$LnG"
  },
  {
    "id": "47",
    "name": "Унайбаева Жанна Сериковна",
    "login": "unaybaeva.zha77",
    "password": "4hc@GLhgBD6f"
  },
  {
    "id": "48",
    "name": "Нұрбек Жансая",
    "login": "nurbek.zha83",
    "password": "baWgQggf$3x7"
  },
  {
    "id": "49",
    "name": "Оспанова Жанна Тулебаевна",
    "login": "ospanova.zha79",
    "password": "#CF9zHzGmjuK"
  },
  {
    "id": "50",
    "name": "Максутов Жандос Амирбекович",
    "login": "maksutov.zha29",
    "password": "W3wa@NmkwJxK"
  },
  {
    "id": "51",
    "name": "Вэнь Жушуан",
    "login": "ven.zhu34",
    "password": "tY3cg5Sx6$DR"
  },
  {
    "id": "52",
    "name": "Давренбекова Жазира Медеткызы",
    "login": "davrenbekova.zha21",
    "password": "DeUwNK3$3aw3"
  },
  {
    "id": "53",
    "name": "Әміртай Әлимарғұлан Азаматханұлы",
    "login": "amirtay.ali50",
    "password": "72Nrmd#qbbkG"
  },
  {
    "id": "54",
    "name": "Байділда Діңмұхаммед Науанұлы",
    "login": "baydilda.din38",
    "password": "dP5GGj@U5CHy"
  },
  {
    "id": "55",
    "name": "Тугаева Алия Абдуалиевна",
    "login": "tugaeva.ali63",
    "password": "j214wnLF!UGy"
  },
  {
    "id": "56",
    "name": "Булатов Алихан Даулетович",
    "login": "bulatov.ali75",
    "password": "fTWReVxHt$7H"
  },
  {
    "id": "57",
    "name": "Борамбаева Адель Руслановна",
    "login": "borambaeva.ade49",
    "password": "Q8LdUd7Z3R!F"
  },
  {
    "id": "58",
    "name": "Сакып Батухан",
    "login": "sakyp.bat72",
    "password": "a503vXA#9NJu"
  },
  {
    "id": "59",
    "name": "Куаныш Даниал",
    "login": "kuanysh.dan56",
    "password": "Bwqfw6USP!Dk"
  },
  {
    "id": "60",
    "name": "Назенов Алишер Рашитулы",
    "login": "nazenov.ali57",
    "password": "$k6Sk0LNSn5E"
  },
  {
    "id": "61",
    "name": "Дәулетқан Ажар Әділетқызы",
    "login": "dauletqan.azh92",
    "password": "sJ6Kf1#xWTLh"
  },
  {
    "id": "62",
    "name": "Ескендиров Арсен Маратулы",
    "login": "eskendirov.ars81",
    "password": "5YsJn@zXjhEs"
  },
  {
    "id": "63",
    "name": "Карабай Алдияр",
    "login": "karabay.ald81",
    "password": "Fv7ws5w3n9P$"
  },
  {
    "id": "64",
    "name": "Кудреватых Данияр Евгеньевич",
    "login": "kudrevatyh.dan66",
    "password": "rj8DjZG%B8Ls"
  },
  {
    "id": "65",
    "name": "Салжанов Тамерлан Арысланович",
    "login": "salzhanov.tam72",
    "password": "bA3KkbmA@rZs"
  },
  {
    "id": "66",
    "name": "Каиров Милас",
    "login": "kairov.mil19",
    "password": "QFgZFJVX@31n"
  },
  {
    "id": "67",
    "name": "Бакдаулет Даурен Нурланович",
    "login": "bakdaulet.dau23",
    "password": "HK5@wZ99dQ35"
  },
  {
    "id": "68",
    "name": "Рсбай Чингиз Маликулы",
    "login": "rsbay.chi31",
    "password": "yPq@xgG9ZE48"
  },
  {
    "id": "69",
    "name": "Әлихан Әшим",
    "login": "alihan.ash35",
    "password": "zBEe19Zhj%uH"
  },
  {
    "id": "70",
    "name": "Канапина Милана",
    "login": "kanapina.mil91",
    "password": "UKcDzEF6x@cU"
  },
  {
    "id": "71",
    "name": "Гайсенова Ясмина Маратовна",
    "login": "gaysenova.yas85",
    "password": "v4PhB#39SCwA"
  },
  {
    "id": "72",
    "name": "Кадырали Мухамеджан Бауыржанулы",
    "login": "kadyrali.muh58",
    "password": "dd8qHRHw6%74"
  },
  {
    "id": "73",
    "name": "Аскар",
    "login": "askar83",
    "password": "mWfpEqV!NX77"
  },
  {
    "id": "74",
    "name": "Анель Нысанбаева",
    "login": "anel.nys77",
    "password": "xtqaJM8bBcP%"
  },
  {
    "id": "75",
    "name": "Адильбек Мухамеджан",
    "login": "adilbek.muh22",
    "password": "hmA0s5EbSZA!"
  },
  {
    "id": "76",
    "name": "Мерсагатова Аруниса Газизхановна",
    "login": "mersagatova.aru58",
    "password": "bJ2VkWhgHXK#"
  },
  {
    "id": "77",
    "name": "Берекпол Әділмансур",
    "login": "berekpol.adi69",
    "password": "Qreb!LEC5M0N"
  },
  {
    "id": "78",
    "name": "Наманбек Адия рустемкызы",
    "login": "namanbek.adi91",
    "password": "QpJ@SU8ya7KK"
  },
  {
    "id": "79",
    "name": "Жакишев Мансур Талгатулы",
    "login": "zhakishev.man93",
    "password": "X6BqdQA#yAfJ"
  },
  {
    "id": "80",
    "name": "Мусеркегенов Динмухамед Нагметович",
    "login": "muserkegenov.din30",
    "password": "e6tBj%V996x5"
  },
  {
    "id": "81",
    "name": "Кожмухаметова Дильназ Динмухаметқызы",
    "login": "kozhmuhametova.dil93",
    "password": "UJ3nDy@sTTDF"
  },
  {
    "id": "82",
    "name": "Туркия Шыңғыс Жеңісұлы",
    "login": "turkiya.shy67",
    "password": "y4gHYPm8Fw9$"
  },
  {
    "id": "83",
    "name": "Каирбаев Алишер Нуржанович",
    "login": "kairbaev.ali72",
    "password": "Z53@ys3MtpLU"
  },
  {
    "id": "84",
    "name": "Муратов Амир Ержанулы",
    "login": "muratov.ami88",
    "password": "EcNED#5FbuqL"
  },
  {
    "id": "85",
    "name": "Максут Динмухаммед Максатович",
    "login": "maksut.din12",
    "password": "ZFWnehAf#Bw7"
  },
  {
    "id": "86",
    "name": "Абай Елжан Ренатулы",
    "login": "abay.elz78",
    "password": "3h7%75U7jH3k"
  },
  {
    "id": "87",
    "name": "Сегизбай Айтуар Саматович",
    "login": "segizbay.ayt86",
    "password": "YZ#twp2NZHAu"
  },
  {
    "id": "88",
    "name": "Асылхан Зангар",
    "login": "asylhan.zan10",
    "password": "DGv5ZHaWk@K0"
  },
  {
    "id": "89",
    "name": "Каратаева Айдана Амангельдиевна",
    "login": "karataeva.ayd62",
    "password": "#gEN1QkYyfCE"
  },
  {
    "id": "90",
    "name": "Дуйсен Мейрам Ерикулы",
    "login": "duysen.mey58",
    "password": "Nkz@dY9VgNUJ"
  },
  {
    "id": "91",
    "name": "Асланова Амина Асланова",
    "login": "aslanova.ami91",
    "password": "DCG3GZaYA5#f"
  },
  {
    "id": "92",
    "name": "Шабанова Инжу Ренатовна",
    "login": "shabanova.inz64",
    "password": "20PM@cNMCfqS"
  },
  {
    "id": "93",
    "name": "Зайров Изтилеу Тлепбергенович",
    "login": "zayrov.izt88",
    "password": "q$7VNyVcS8Am"
  },
  {
    "id": "94",
    "name": "Мажит Назерке Дарханкызы",
    "login": "mazhit.naz55",
    "password": "x8b7#GaWNcq8"
  },
  {
    "id": "95",
    "name": "Оразалы Аружан 10 класс 2026",
    "login": "orazaly.aru99",
    "password": "MjJrc2tzNYz#"
  },
  {
    "id": "96",
    "name": "Калабай Нурбек Аманжолулы",
    "login": "kalabay.nur17",
    "password": "CCjq86qcV2D%"
  },
  {
    "id": "97",
    "name": "Оразбаева Аида",
    "login": "orazbaeva.aid38",
    "password": "5TDZXn%p3YJ5"
  },
  {
    "id": "98",
    "name": "Зиенгалиев Санжар",
    "login": "ziengaliev.san88",
    "password": "E%4BM9xXe4PV"
  },
  {
    "id": "99",
    "name": "Мустапина Айгерим Ринаткызы",
    "login": "mustapina.ayg75",
    "password": "3$LVqb5MMy5q"
  },
  {
    "id": "100",
    "name": "Амантай Әмина",
    "login": "amantay.ami65",
    "password": "NEz30d4%Zrb2"
  },
  {
    "id": "101",
    "name": "Алимбекова Милат Ерлановна",
    "login": "alimbekova.mil85",
    "password": "$TdCGh7qJMBy"
  },
  {
    "id": "102",
    "name": "Бактыбай Жансая Орлханкызы",
    "login": "baktybay.zha18",
    "password": "Fa2RqUJxY@jK"
  },
  {
    "id": "103",
    "name": "Оракеев Артур",
    "login": "orakeev.art34",
    "password": "vv73LB3d%Nfc"
  },
  {
    "id": "104",
    "name": "Торебек Махамбет",
    "login": "torebek.mah20",
    "password": "uaZSj7uhg2q@"
  },
  {
    "id": "105",
    "name": "Ильяс Серикбаев",
    "login": "ilyas.ser11",
    "password": "FJw%4W9BMy2T"
  },
  {
    "id": "106",
    "name": "Госман Али",
    "login": "gosman.ali10",
    "password": "2@7Q7eSBE26z"
  },
  {
    "id": "107",
    "name": "Бекешов Ыбырай Асыланович",
    "login": "bekeshov.yby97",
    "password": "jmvXvf9#21L5"
  },
  {
    "id": "108",
    "name": "Адильхан Кайрат",
    "login": "adilhan.kay37",
    "password": "fFs9Uy55%S2h"
  },
  {
    "id": "109",
    "name": "Дарханкызы Енлик",
    "login": "darhankyzy.enl71",
    "password": "F22ujw$aqBMa"
  },
  {
    "id": "110",
    "name": "Апишова Гульвира Байсалбековна",
    "login": "apishova.gul40",
    "password": "3erbDmQP#E1S"
  },
  {
    "id": "111",
    "name": "Ерсаинова Мира Кадыржановна",
    "login": "ersainova.mir84",
    "password": "Jz8MQK%CAnHk"
  },
  {
    "id": "112",
    "name": "Далабаева Ясмина Ринатовна",
    "login": "dalabaeva.yas18",
    "password": "@WN3QeVqBHeW"
  },
  {
    "id": "113",
    "name": "Серікбай Ұлпан",
    "login": "serikbay.ulp72",
    "password": "T$7r4z85Q2zg"
  },
  {
    "id": "114",
    "name": "Рахимов Джалиль Тимурович",
    "login": "rahimov.dzh88",
    "password": "5Rg1FgM%YZbT"
  },
  {
    "id": "115",
    "name": "Этмахамбетова Адия Тимуровна",
    "login": "etmahambetova.adi69",
    "password": "4jS%T5QNFUvf"
  },
  {
    "id": "116",
    "name": "Қырғи Аиша Есқалиқызы",
    "login": "qyrgi.ais12",
    "password": "@56teU8vUJCe"
  },
  {
    "id": "117",
    "name": "Закіржан Нұрия Елдосқызы",
    "login": "zakirzhan.nur79",
    "password": "yUetV8g32wr!"
  },
  {
    "id": "118",
    "name": "Колупаева Агафья Борисовна",
    "login": "kolupaeva.aga63",
    "password": "4NKM@EjLCcJS"
  },
  {
    "id": "119",
    "name": "Әлім Лаура Жеңісқызы",
    "login": "alim.lau59",
    "password": "#mdSW9Mz8VSX"
  },
  {
    "id": "120",
    "name": "Мақсұт Әлихан Мәуленұлы",
    "login": "maqsut.ali63",
    "password": "D3zpX8J4@TzQ"
  },
  {
    "id": "121",
    "name": "Нурдинова Айдана Нургазыевна",
    "login": "nurdinova.ayd96",
    "password": "%gp8gcfYuk2N"
  },
  {
    "id": "122",
    "name": "Куванов",
    "login": "kuvanov79",
    "password": "sCGLac!h0ZcG"
  },
  {
    "id": "123",
    "name": "Омирбекова Акерке Мараткызы",
    "login": "omirbekova.ake44",
    "password": "SG2%ybHPr4Ex"
  },
  {
    "id": "124",
    "name": "Есберген Аселхан Жексенғалиқызы",
    "login": "esbergen.ase65",
    "password": "Q%W3nY6dtm9D"
  },
  {
    "id": "125",
    "name": "Заремба Ева Денисовна",
    "login": "zaremba.eva97",
    "password": "yUfQ%J3zjdXx"
  },
  {
    "id": "126",
    "name": "Кажмуратова Назерке Мадиевна",
    "login": "kazhmuratova.naz45",
    "password": "8p7N7F!dgGRC"
  },
  {
    "id": "127",
    "name": "Кулибаев Бекнур Бауржанович",
    "login": "kulibaev.bek28",
    "password": "JXE9F46cJqz@"
  },
  {
    "id": "128",
    "name": "Камали Алуа Мерейкызы",
    "login": "kamali.alu36",
    "password": "AwRH!y5Mj31S"
  },
  {
    "id": "129",
    "name": "Муслимова Адия Адилевна",
    "login": "muslimova.adi53",
    "password": "PGV4kg9Mj!ym"
  },
  {
    "id": "130",
    "name": "Абдукаримов Мадияр Санжарович",
    "login": "abdukarimov.mad36",
    "password": "3Uk4RLfxgDz!"
  },
  {
    "id": "131",
    "name": "Sasha De Bode",
    "login": "sasha.de65",
    "password": "sTs2kRNMfX#N"
  },
  {
    "id": "132",
    "name": "Петенев Максим Вадимович",
    "login": "petenev.mak98",
    "password": "g2U@r2AZcPqN"
  },
  {
    "id": "133",
    "name": "Бердалина Адэль Ардаққызы",
    "login": "berdalina.ade24",
    "password": "fhcU6!Jpedds"
  },
  {
    "id": "134",
    "name": "Айтжан Айбар Серікұлы",
    "login": "aytzhan.ayb27",
    "password": "whjQcLRrrN8@"
  },
  {
    "id": "135",
    "name": "Беймуратова Амина Маратовна",
    "login": "beymuratova.ami28",
    "password": "4#ska7GC3Emv"
  },
  {
    "id": "136",
    "name": "Айтжан Торехан Айтбайулы",
    "login": "aytzhan.tor63",
    "password": "zA3Uz$qG8Q2f"
  },
  {
    "id": "137",
    "name": "Есенбек Айша Муратовна",
    "login": "esenbek.ays19",
    "password": "76@ALjMD6FXs"
  },
  {
    "id": "138",
    "name": "Каренеева Таира Бахтияровна",
    "login": "kareneeva.tai28",
    "password": "U55pvyRxg@0j"
  },
  {
    "id": "139",
    "name": "Есен Арайлым Аманқызы",
    "login": "esen.ara22",
    "password": "1d2nja$UKGpG"
  },
  {
    "id": "140",
    "name": "Елюбай Шернияз Әуэзұлы",
    "login": "elyubay.she34",
    "password": "DFCQ6qyEg$Hc"
  },
  {
    "id": "141",
    "name": "Сабирбай Махаббат Шыныкулкызы",
    "login": "sabirbay.mah65",
    "password": "2KMuF9RysZ#5"
  },
  {
    "id": "142",
    "name": "Мырзабаева Азиза",
    "login": "myrzabaeva.azi31",
    "password": "k!y34u6bpUaE"
  },
  {
    "id": "143",
    "name": "Қоңыратбай Сымбат Махсатқызы",
    "login": "qonyratbay.sym49",
    "password": "x7nJU%Hhq8fS"
  },
  {
    "id": "144",
    "name": "Толегенова Альбина",
    "login": "tolegenova.alb84",
    "password": "7xnW8Y#CpaQw"
  },
  {
    "id": "145",
    "name": "Есен Абдурахман Саянұлы",
    "login": "esen.abd50",
    "password": "Lh#eQXEPqES9"
  },
  {
    "id": "146",
    "name": "Кеулимжанов  Имангали Жантемирович",
    "login": "keulimzhanov.ima38",
    "password": "fY9uAn9XM#CH"
  },
  {
    "id": "147",
    "name": "Тогобицкий Иван",
    "login": "togobitskiy.iva24",
    "password": "cndrR9c7@Cpe"
  },
  {
    "id": "148",
    "name": "Султанова Элина Гарипуллаевна",
    "login": "sultanova.eli62",
    "password": "Cps@QTj8ufUx"
  },
  {
    "id": "149",
    "name": "Абдугалиев Алидар Ануарович",
    "login": "abdugaliev.ali14",
    "password": "wpeS5t7C2Ew%"
  },
  {
    "id": "150",
    "name": "Байгабулова Аружан Сабитовна",
    "login": "baygabulova.aru44",
    "password": "Tx#S9GRU9cu9"
  },
  {
    "id": "151",
    "name": "Болекбай Камила Айбаркызы",
    "login": "bolekbay.kam88",
    "password": "5fMZz!wQzz2b"
  },
  {
    "id": "152",
    "name": "Султанов Артур-Тамерлан Гарипуллаевич",
    "login": "sultanov.art39",
    "password": "3gJ6NHUXR#DP"
  },
  {
    "id": "153",
    "name": "Гуртовенко Максим Андреевич",
    "login": "gurtovenko.mak91",
    "password": "Qd1KmP%Umg3e"
  },
  {
    "id": "154",
    "name": "Разбекова Амина Арнуровна",
    "login": "razbekova.ami69",
    "password": "#Mxw75HgXAy7"
  },
  {
    "id": "155",
    "name": "Медведева Адеми Мауленовна",
    "login": "medvedeva.ade12",
    "password": "3hj28fBd!byu"
  },
  {
    "id": "156",
    "name": "Ермеков Абзал",
    "login": "ermekov.abz45",
    "password": "92x8bxqb4kp!"
  },
  {
    "id": "157",
    "name": "Саяжанова Айганым Темирбаевна",
    "login": "sayazhanova.ayg95",
    "password": "UsGG4Sbd@1Kx"
  },
  {
    "id": "158",
    "name": "Рудниченко Арина Сергеевна",
    "login": "rudnichenko.ari43",
    "password": "c3Hx$QtRfEJ3"
  },
  {
    "id": "159",
    "name": "Пак Михаил",
    "login": "pak.mih17",
    "password": "7@DsEJCn9N7Q"
  },
  {
    "id": "160",
    "name": "Хасенов Алим Адилевич",
    "login": "hasenov.ali74",
    "password": "Rqr2fKvUS96@"
  },
  {
    "id": "161",
    "name": "Кенесхан Магжан Айдынбекулы",
    "login": "keneshan.mag52",
    "password": "zynBmmcJ@2PN"
  },
  {
    "id": "162",
    "name": "Жумабай Амирлан Кайроллаулы",
    "login": "zhumabay.ami73",
    "password": "vg$6KJ8gt1Es"
  },
  {
    "id": "163",
    "name": "Куянгузов Алан Аныбекович",
    "login": "kuyanguzov.ala49",
    "password": "XeypMpRJX@5s"
  },
  {
    "id": "164",
    "name": "Рахмет Алихан Ренатулы",
    "login": "rahmet.ali22",
    "password": "1TwEJyNn@4QC"
  },
  {
    "id": "165",
    "name": "Утимбеков Санжар Гарифоллаевич",
    "login": "utimbekov.san64",
    "password": "rKHXtU#0UUML"
  }
]